oasis/__init__.py
oasis/apps.py
oasis/coffee_offers/__init__.py
oasis/coffee_offers/admin.py
oasis/coffee_offers/admin_views.py
oasis/coffee_offers/apps.py
oasis/coffee_offers/urls.py
oasis/coffee_offers/api/__init__.py
oasis/coffee_offers/api/serializers/__init__.py
oasis/coffee_offers/api/serializers/coffee_ware_house.py
oasis/coffee_offers/api/serializers/offer.py
oasis/coffee_offers/api/services/__init__.py
oasis/coffee_offers/api/services/coffee_offers.py
oasis/coffee_offers/lib/__init__.py
oasis/coffee_offers/lib/choices/__init__.py
oasis/coffee_offers/lib/choices/coffee_offers_states.py
oasis/coffee_offers/lib/choices/oasis_choices.py
oasis/coffee_offers/lib/events/__init__.py
oasis/coffee_offers/lib/events/on_post_save_offer.py
oasis/coffee_offers/lib/utils/__init__.py
oasis/coffee_offers/lib/utils/offer_state_machine.py
oasis/coffee_offers/lib/validators/__init__.py
oasis/coffee_offers/lib/validators/date_validators.py
oasis/coffee_offers/lib/validators/oasis_statuses.py
oasis/coffee_offers/locale/es/LC_MESSAGES/django.mo
oasis/coffee_offers/locale/es/LC_MESSAGES/django.po
oasis/coffee_offers/tasks/__init__.py
oasis/coffee_offers/tasks/sync_coffe_offers.py
oasis/coffee_offers/templates/change_status.html
oasis/coffee_offers/templates/change_status.txt
oasis/coffee_offers/templates/save_offer.html
oasis/coffee_offers/templates/save_offer.txt
oasis/coffee_offers/templates/coffee_offers/coffee_notification.html
oasis/coffee_offers/templates/coffee_offers/coffee_offer.html
oasis/coffee_offers/templates/coffee_offers/coffee_offers_base.html
oasis/coffee_offers/templates/coffee_offers/contract_template.html
oasis/coffee_offers/templates/coffee_offers/intention_letter.html
oasis/coffee_offers/templates/coffee_offers/promissory_note.html
oasis/coffee_offers/templates/coffee_offers/remittance_letter.html
oasis/lib/__init__.py
oasis/lib/choices/__init__.py
oasis/lib/choices/customer_type.py
oasis/lib/managers/__init__.py
oasis/lib/managers/local_coffee_ware_house.py
django_oasis4-1.1.2.dist-info/LICENSE
django_oasis4-1.1.2.dist-info/METADATA
django_oasis4-1.1.2.dist-info/WHEEL
django_oasis4-1.1.2.dist-info/top_level.txt
django_oasis4-1.1.2.dist-info/RECORD
