Metadata-Version: 2.1
Name: django-oasis4
Version: 1.1.2
Summary: OASIS4 Data Interfaces
Author-email: Mario Cerón <mario.ceron@cqinversiones.co>
License: CQ INVERSIONES S.A.S.
Keywords: django,cadefihuila
Classifier: License :: Other/Proprietary License
Classifier: Programming Language :: Python :: 3.9
Classifier: Development Status :: 5 - Production/Stable
Classifier: Framework :: Django
Classifier: Framework :: Django :: 4.1
Classifier: Environment :: Web Environment
Classifier: Operating System :: OS Independent
Classifier: Topic :: Internet :: WWW/HTTP
Requires-Python: >=3.9
License-File: LICENSE
Requires-Dist: Django (>=4.1)
Requires-Dist: cx-Oracle
Requires-Dist: celery (>=5.2.7)
Requires-Dist: django-celery-beat
Requires-Dist: zibanu-django (>=1.2.0a11)
Requires-Dist: num2words
